uun_qrdoorlock/__init__.py
uun_qrdoorlock/hw.py
uun_qrdoorlock/data/sample-config.json
uun_qrdoorlock/data/start.sh
uun_qrdoorlock/data/systemd.service
uun_qrdoorlock/modules/DoorMonitor.py
uun_qrdoorlock/modules/QrLock.py
uun_qrdoorlock/modules/__init__.py
uun_qrdoorlock-0.5.5.data/scripts/uun-qrdoorlock
uun_qrdoorlock-0.5.5.data/scripts/uun-qrdoorlock-install
uun_qrdoorlock-0.5.5.dist-info/LICENSE.md
uun_qrdoorlock-0.5.5.dist-info/METADATA
uun_qrdoorlock-0.5.5.dist-info/WHEEL
uun_qrdoorlock-0.5.5.dist-info/top_level.txt
uun_qrdoorlock-0.5.5.dist-info/RECORD
