Metadata-Version: 2.1
Name: uun-qrdoorlock
Version: 0.5.5
Summary: Decode a signed QR code and open electronic door lock.
Home-page: https://uuos9.plus4u.net/uu-bookkitg01-main/0576be9b7afc47ceb030483cb66174c7/book/page?code=home
Author: (UUN) Tomáš Faikl
Author-email: tomas.faikl@unicornuniversity.net
Classifier: Programming Language :: Python :: 3
Classifier: License :: OSI Approved :: MIT License
Requires-Python: >=3.6
License-File: LICENSE.md
Requires-Dist: uun-iot >=0.10.0
Requires-Dist: pyserial
Requires-Dist: pynacl
Requires-Dist: validators
Requires-Dist: termcolor
